pyscience/__init__.py
pyscience/__main__.py
pyscience/fraction.py
pyscience/interpreter.py
pyscience/parser.py
pyscience/algebra/__init__.py
pyscience/algebra/equation.py
pyscience/algebra/monomial.py
pyscience/algebra/polynomial.py
pyscience/algebra/variable.py
pyscience/chemistry/__init__.py
pyscience/chemistry/element.py
pyscience/chemistry/periodic_table.csv
pyscience/datam/__init__.py
pyscience/math/__init__.py
pyscience/math/fraction.py
pyscience/math/number.py
pyscience/units/__init__.py
pyscience/units/unitparser.py
pyscience/units/units.txt
pyscience-0.5.0.dist-info/LICENSE
pyscience-0.5.0.dist-info/METADATA
pyscience-0.5.0.dist-info/WHEEL
pyscience-0.5.0.dist-info/entry_points.txt
pyscience-0.5.0.dist-info/top_level.txt
pyscience-0.5.0.dist-info/RECORD
